aismt/__init__.py
aismt/api.py
aismt/app.py
aismt/cli.py
aismt-23.11.30.dist-info/METADATA
aismt-23.11.30.dist-info/WHEEL
aismt-23.11.30.dist-info/entry_points.txt
aismt-23.11.30.dist-info/RECORD
