Metadata-Version: 2.1
Name: aismt
Version: 23.11.30
Summary: A command-line interface for AI Smart Task.
Home-page: https://github.com/chatmangpt/aismt
Author: Sean Chatman
Author-email: info@chatmangpt.com
Requires-Python: >=3.11,<4.0
Classifier: Programming Language :: Python :: 3
Classifier: Programming Language :: Python :: 3.11
Classifier: Programming Language :: Python :: 3.12
Requires-Dist: aiofiles (>=23.2.1,<24.0.0)
Requires-Dist: aiohttp (>=3.9.0,<4.0.0)
Requires-Dist: anyio (==3.7.1)
Requires-Dist: astor (>=0.8.1,<0.9.0)
Requires-Dist: autopep8 (>=2.0.4,<3.0.0)
Requires-Dist: coloredlogs (>=15.0.1)
Requires-Dist: duckduckgo-search (>=3.9.6,<4.0.0)
Requires-Dist: email-validator (>=2.1.0.post1,<3.0.0)
Requires-Dist: factory-boy (>=3.3.0,<4.0.0)
Requires-Dist: faker (>=20.1.0,<21.0.0)
Requires-Dist: fastapi[all] (>=0.92.0)
Requires-Dist: gitpython (>=3.1.40,<4.0.0)
Requires-Dist: gunicorn (>=20.1.0)
Requires-Dist: icalendar (>=5.0.11,<6.0.0)
Requires-Dist: icontract (>=2.6.6,<3.0.0)
Requires-Dist: inflection (>=0.5.1,<0.6.0)
Requires-Dist: jinja2 (>=3.1.2,<4.0.0)
Requires-Dist: jinja2-time (>=0.2.0,<0.3.0)
Requires-Dist: jupyter (>=1.0.0,<2.0.0)
Requires-Dist: loguru (>=0.7.2,<0.8.0)
Requires-Dist: matplotlib (>=3.8.2,<4.0.0)
Requires-Dist: munch (>=4.0.0,<5.0.0)
Requires-Dist: openai (>=1.3.5,<2.0.0)
Requires-Dist: pandas (>=2.1.3,<3.0.0)
Requires-Dist: poethepoet (>=0.20.0)
Requires-Dist: pydantic (>=1.10.7)
Requires-Dist: pyperclip (>=1.8.2,<2.0.0)
Requires-Dist: pyppeteer (>=1.0.2,<2.0.0)
Requires-Dist: pyshacl (>=0.25.0,<0.26.0)
Requires-Dist: pytest-bdd (>=7.0.0,<8.0.0)
Requires-Dist: python-dateutil (>=2.8.2,<3.0.0)
Requires-Dist: python-multipart (>=0.0.6,<0.0.7)
Requires-Dist: pytz (>=2023.3.post1,<2024.0)
Requires-Dist: radon (>=6.0.1,<7.0.0)
Requires-Dist: rdflib (>=7.0.0,<8.0.0)
Requires-Dist: redbaron (>=0.9.2,<0.10.0)
Requires-Dist: sismic (>=1.6.6,<2.0.0)
Requires-Dist: sqlmodel (>=0.0.12,<0.0.13)
Requires-Dist: streamlit (>=1.19.0)
Requires-Dist: typer[all] (>=0.9.0)
Requires-Dist: tzlocal (>=5.2,<6.0)
Requires-Dist: uvicorn[standard] (>=0.20.0)
Project-URL: Repository, https://github.com/chatmangpt/aismt
